<mediaList>
  <media>
    <title>EarthCam Live:  Times Square in 4K</title>
    <thumb>https://img.youtube.com/vi/rnXIjl_Rzy4/0.jpg</thumb>
    <type>youtube</type>
    <src>rnXIjl_Rzy4</src>
  </media><media>
    <title>EarthCam Live:  Niagara Falls</title>
    <thumb>https://img.youtube.com/vi/qx7gry390YA/0.jpg</thumb>
    <type>youtube</type>
    <src>qx7gry390YA</src>
  </media><media>
    <title>EarthCam Live - Western Wall  (Jerusalem, Israel)</title>
    <thumb>https://img.youtube.com/vi/77akujLn4k8/0.jpg</thumb>
    <type>youtube</type>
    <src>77akujLn4k8</src>
  </media><media>
    <title>EarthCam Live:  Midway Airport (Chicago, IL)</title>
    <thumb>https://img.youtube.com/vi/0ZzPWoeZzuI/0.jpg</thumb>
    <type>youtube</type>
    <src>0ZzPWoeZzuI</src>
  </media><media>
    <title>EarthCam Live:  Wildwoods Cam (Wildwood, NJ)</title>
    <thumb>https://img.youtube.com/vi/58Lx2eLT1ig/0.jpg</thumb>
    <type>youtube</type>
    <src>58Lx2eLT1ig</src>
  </media><media>
    <title>🔴 LIVE 24/7  Rolling Cam Venice - Live Cam in Venice Italy - Livecam en direct #venice</title>
    <thumb>https://img.youtube.com/vi/a1mcaV3Sf9U/0.jpg</thumb>
    <type>youtube</type>
    <src>a1mcaV3Sf9U</src>
  </media><media>
    <title>🔴 Live Cam around the World - Rolling Cam with Chill &amp;amp; Lounge Music</title>
    <thumb>https://img.youtube.com/vi/i10aOLMK76k/0.jpg</thumb>
    <type>youtube</type>
    <src>i10aOLMK76k</src>
  </media><media>
    <title>🔴 4K View of the Ponte delle Guglie and Strada Nova - Live Stream from Hotel Marte Venice</title>
    <thumb>https://img.youtube.com/vi/GQbUdGhHw_o/0.jpg</thumb>
    <type>youtube</type>
    <src>GQbUdGhHw_o</src>
  </media><media>
    <title>🔴 Venice Live Cam - Laguna of Venice with 4K Cam PTZ 30x - Stream from Cantieri Biasin</title>
    <thumb>https://img.youtube.com/vi/Ts4cAVmJrWE/0.jpg</thumb>
    <type>youtube</type>
    <src>Ts4cAVmJrWE</src>
  </media><media>
    <title>🔴 Venice Italy Live Cam - Rialto Bridge in Live Streaming from Palazzo Bembo - Live Webcam - ライブカメラ</title>
    <thumb>https://img.youtube.com/vi/CMn6xQXuSjI/0.jpg</thumb>
    <type>youtube</type>
    <src>CMn6xQXuSjI</src>
  </media><media>
    <title>The World Live - Original Version | earthTV®</title>
    <thumb>https://img.youtube.com/vi/HfgIFGbdGJ0/0.jpg</thumb>
    <type>youtube</type>
    <src>HfgIFGbdGJ0</src>
  </media><media>
    <title>🔴 Mersea Restaurant LIVE Bay View · San Francisco Skyline, Golden Gate &amp;amp; Luxury Waterfront 🌉</title>
    <thumb>https://img.youtube.com/vi/BSWhGNXxT9A/0.jpg</thumb>
    <type>youtube</type>
    <src>BSWhGNXxT9A</src>
  </media><media>
    <title>🔴 Los Angeles Live Cam · Venice Beach · Venice V Hotel · Live Camera Stream</title>
    <thumb>https://img.youtube.com/vi/EO_1LWqsCNE/0.jpg</thumb>
    <type>youtube</type>
    <src>EO_1LWqsCNE</src>
  </media><media>
    <title>🔴 Beach Live Stream · House of Sanskara · Koh Phangan, Thailand</title>
    <thumb>https://img.youtube.com/vi/FBYUkqutqzE/0.jpg</thumb>
    <type>youtube</type>
    <src>FBYUkqutqzE</src>
  </media><media>
    <title>👑🅻🅸🆅🅴👑United Kingdom Seaside Webcams Tour🏖️Scotland Wales Cornwall Shores🌅England👑British Coast LIVE</title>
    <thumb>https://img.youtube.com/vi/K2gBg7jjhIc/0.jpg</thumb>
    <type>youtube</type>
    <src>K2gBg7jjhIc</src>
  </media><media>
    <title>🟦🅻🅸🆅🅴⭐European Webcam Journey🎥A panoramic tour of 280 Europe’s cities and landscapes🎇Paris Rome😍</title>
    <thumb>https://img.youtube.com/vi/zmv6NPLg91U/0.jpg</thumb>
    <type>youtube</type>
    <src>zmv6NPLg91U</src>
  </media><media>
    <title>🌅🅻🅸🆅🅴🌅Cornwall Coast Webcams Tour🌊Harbour &amp;amp; Beach🌪️England 🇬🇧 Waves🌬️Wind St Ives,Marazion,Newquay</title>
    <thumb>https://img.youtube.com/vi/9RuV9Cc-LSA/0.jpg</thumb>
    <type>youtube</type>
    <src>9RuV9Cc-LSA</src>
  </media><media>
    <title>🌍🅻🅸🆅🅴🌍Worldwide Webcam Tour📸Watch 500 Random Cams From All Around the World🗺️London Paris Sydnei🌠</title>
    <thumb>https://img.youtube.com/vi/yvt5GtJVKYM/0.jpg</thumb>
    <type>youtube</type>
    <src>yvt5GtJVKYM</src>
  </media><media>
    <title>❄️🅻🅸🆅🅴❄️Siberia Spring Edition Webcam Tour🌏50 Cams Real Life Exposed🚫No Propaganda🌱Life After Winter</title>
    <thumb>https://img.youtube.com/vi/tHf8xbUNlTU/0.jpg</thumb>
    <type>youtube</type>
    <src>tHf8xbUNlTU</src>
  </media><media>
    <title>LIVE NEWS: FOX LOCAL NY 24/7 Live Stream</title>
    <thumb>https://img.youtube.com/vi/ADXWeM9wsDw/0.jpg</thumb>
    <type>youtube</type>
    <src>ADXWeM9wsDw</src>
  </media><media>
    <title>🔴 24/7 NYC Live Cam | Times Square, skyline, streets, more</title>
    <thumb>https://img.youtube.com/vi/VGnFLdQW39A/0.jpg</thumb>
    <type>youtube</type>
    <src>VGnFLdQW39A</src>
  </media><media>
    <title>Bryant Park Webcam</title>
    <thumb>https://img.youtube.com/vi/JPxiYF2fSC8/0.jpg</thumb>
    <type>youtube</type>
    <src>JPxiYF2fSC8</src>
  </media><media>
    <title>Pier 23 Cafe, San Francisco Bay | San Francisco, CA USA | StreamTime LIVE</title>
    <thumb>https://img.youtube.com/vi/a5IW4I-z2rs/0.jpg</thumb>
    <type>youtube</type>
    <src>a5IW4I-z2rs</src>
  </media><media>
    <title>LIVE CAM: Ohio River, Jeffersonville, IN | StreamTime LIVE</title>
    <thumb>https://img.youtube.com/vi/MqzQdTHCTOg/0.jpg</thumb>
    <type>youtube</type>
    <src>MqzQdTHCTOg</src>
  </media><media>
    <title>Marine City, Michigan, USA | StreamTime LIVE</title>
    <thumb>https://img.youtube.com/vi/F_bENs4GV24/0.jpg</thumb>
    <type>youtube</type>
    <src>F_bENs4GV24</src>
  </media><media>
    <title>Lake Hood Seaplane Base, Anchorage, Alaska, USA | StreamTime LIVE</title>
    <thumb>https://img.youtube.com/vi/61pi8UjLOlo/0.jpg</thumb>
    <type>youtube</type>
    <src>61pi8UjLOlo</src>
  </media><media>
    <title>Midway Airport | Chicago, IL USA | StreamTime LIVE  4K</title>
    <thumb>https://img.youtube.com/vi/67BCsiW-1Io/0.jpg</thumb>
    <type>youtube</type>
    <src>67BCsiW-1Io</src>
  </media><media>
    <title>Live NYC Brooklyn Bridge &amp;amp; Manhattan cam</title>
    <thumb>https://img.youtube.com/vi/siVyh-5zsUM/0.jpg</thumb>
    <type>youtube</type>
    <src>siVyh-5zsUM</src>
  </media><media>
    <title>Live NYC Lower Manhattan &amp;amp; New York Harbor Cam</title>
    <thumb>https://img.youtube.com/vi/ZM-JxBHy1QU/0.jpg</thumb>
    <type>youtube</type>
    <src>ZM-JxBHy1QU</src>
  </media><media>
    <title>Times Square: Duffy Square 4K View Live</title>
    <thumb>https://img.youtube.com/vi/iiBTWU2FyFo/0.jpg</thumb>
    <type>youtube</type>
    <src>iiBTWU2FyFo</src>
  </media><media>
    <title>Times Square: 1560 Broadway View Live</title>
    <thumb>https://img.youtube.com/vi/4qyZLflp-sI/0.jpg</thumb>
    <type>youtube</type>
    <src>4qyZLflp-sI</src>
  </media><media>
    <title>Times Square: Express View Live</title>
    <thumb>https://img.youtube.com/vi/a9J1OP_x5Rg/0.jpg</thumb>
    <type>youtube</type>
    <src>a9J1OP_x5Rg</src>
  </media><media>
    <title>Times Square: 1515 Broadway View Live</title>
    <thumb>https://img.youtube.com/vi/VSSHILnbfyw/0.jpg</thumb>
    <type>youtube</type>
    <src>VSSHILnbfyw</src>
  </media><media>
    <title>Times Square: 1540 Broadway View Live</title>
    <thumb>https://img.youtube.com/vi/nVsDt8AvfCU/0.jpg</thumb>
    <type>youtube</type>
    <src>nVsDt8AvfCU</src>
  </media><media>
    <title>Live Stream — Public Square, Watertown NY — Jake Johnson Properties</title>
    <thumb>https://img.youtube.com/vi/Zz9hMrxl20I/0.jpg</thumb>
    <type>youtube</type>
    <src>Zz9hMrxl20I</src>
  </media><media>
    <title>Live Stream — Public Square, Watertown NY</title>
    <thumb>https://img.youtube.com/vi/vaDjY-5Ymxc/0.jpg</thumb>
    <type>youtube</type>
    <src>vaDjY-5Ymxc</src>
  </media><media>
    <title>Live Stream — McLear’s Cottage Colony &amp;amp; Campground, Black Lake, NY</title>
    <thumb>https://img.youtube.com/vi/CTJTsAc53KY/0.jpg</thumb>
    <type>youtube</type>
    <src>CTJTsAc53KY</src>
  </media><media>
    <title>Live Stream — Dry Hill Ski Area, Watertown NY</title>
    <thumb>https://img.youtube.com/vi/d3QkaaLkUHg/0.jpg</thumb>
    <type>youtube</type>
    <src>d3QkaaLkUHg</src>
  </media><media>
    <title>Hamptons.com - LIVE! 4K Main Street, Sag Harbor Village, New York</title>
    <thumb>https://img.youtube.com/vi/sxZxz0OPoh0/0.jpg</thumb>
    <type>youtube</type>
    <src>sxZxz0OPoh0</src>
  </media><media>
    <title>Hamptons.com - LIVE SURF CAM! Ponquogue Beach Pavilion, Hampton Bays, New York</title>
    <thumb>https://img.youtube.com/vi/XL4p6oiP9zs/0.jpg</thumb>
    <type>youtube</type>
    <src>XL4p6oiP9zs</src>
  </media><media>
    <title>Hamptons.com - LIVE! 4K Main Beach, East Hampton Village, New York - Hamptons Surf Report</title>
    <thumb>https://img.youtube.com/vi/yLU8DNeXXmc/0.jpg</thumb>
    <type>youtube</type>
    <src>yLU8DNeXXmc</src>
  </media><media>
    <title>Hamptons.com - LIVE! Tiana Beach, Hampton Bays, New York</title>
    <thumb>https://img.youtube.com/vi/63Bi7YXdUAY/0.jpg</thumb>
    <type>youtube</type>
    <src>63Bi7YXdUAY</src>
  </media><media>
    <title>Hamptons.com - LIVE! Long Wharf, Sag Harbor, New York (HARBOR CAM)</title>
    <thumb>https://img.youtube.com/vi/bBNay8b8Q74/0.jpg</thumb>
    <type>youtube</type>
    <src>bBNay8b8Q74</src>
  </media><media>
    <title>Live Cameras Around the World - Music, Timelapse, Travel</title>
    <thumb>https://img.youtube.com/vi/AiNCbGzabVo/0.jpg</thumb>
    <type>youtube</type>
    <src>AiNCbGzabVo</src>
  </media><media>
    <title>New England Springtime is LIVE - Webcams, Weather, Music, Timelapse</title>
    <thumb>https://img.youtube.com/vi/x_ruIH2UmjQ/0.jpg</thumb>
    <type>youtube</type>
    <src>x_ruIH2UmjQ</src>
  </media><media>
    <title>Effingham, New Hampshire  -  CAM 2</title>
    <thumb>https://img.youtube.com/vi/DTlS71DA-es/0.jpg</thumb>
    <type>youtube</type>
    <src>DTlS71DA-es</src>
  </media><media>
    <title>Fryeburg, Maine - 302 West</title>
    <thumb>https://img.youtube.com/vi/QcNfT_tvkyI/0.jpg</thumb>
    <type>youtube</type>
    <src>QcNfT_tvkyI</src>
  </media><media>
    <title>Live Outdoor Skating Rink - Patio Cam 1 from Portsmouth, New Hampshire - Strawbery Banke</title>
    <thumb>https://img.youtube.com/vi/PoZ1Hy7PQig/0.jpg</thumb>
    <type>youtube</type>
    <src>PoZ1Hy7PQig</src>
  </media><media>
    <title>🔴 Mersea Restaurant LIVE Bay View · San Francisco Skyline, Golden Gate &amp;amp; Luxury Waterfront 🌉</title>
    <thumb>https://img.youtube.com/vi/BSWhGNXxT9A/0.jpg</thumb>
    <type>youtube</type>
    <src>BSWhGNXxT9A</src>
  </media><media>
    <title>🔴 Los Angeles Live Cam · Venice Beach · Venice V Hotel · Live Camera Stream</title>
    <thumb>https://img.youtube.com/vi/EO_1LWqsCNE/0.jpg</thumb>
    <type>youtube</type>
    <src>EO_1LWqsCNE</src>
  </media><media>
    <title>🔴 Beach Live Stream · House of Sanskara · Koh Phangan, Thailand</title>
    <thumb>https://img.youtube.com/vi/FBYUkqutqzE/0.jpg</thumb>
    <type>youtube</type>
    <src>FBYUkqutqzE</src>
  </media><media>
    <title>🔴 LIVE 24/7  Rolling Cam Venice - Live Cam in Venice Italy - Livecam en direct #venice</title>
    <thumb>https://img.youtube.com/vi/a1mcaV3Sf9U/0.jpg</thumb>
    <type>youtube</type>
    <src>a1mcaV3Sf9U</src>
  </media><media>
    <title>🔴 Live Cam around the World - Rolling Cam with Chill &amp;amp; Lounge Music</title>
    <thumb>https://img.youtube.com/vi/i10aOLMK76k/0.jpg</thumb>
    <type>youtube</type>
    <src>i10aOLMK76k</src>
  </media><media>
    <title>🔴 4K View of the Ponte delle Guglie and Strada Nova - Live Stream from Hotel Marte Venice</title>
    <thumb>https://img.youtube.com/vi/GQbUdGhHw_o/0.jpg</thumb>
    <type>youtube</type>
    <src>GQbUdGhHw_o</src>
  </media><media>
    <title>🔴 Venice Live Cam - Laguna of Venice with 4K Cam PTZ 30x - Stream from Cantieri Biasin</title>
    <thumb>https://img.youtube.com/vi/Ts4cAVmJrWE/0.jpg</thumb>
    <type>youtube</type>
    <src>Ts4cAVmJrWE</src>
  </media><media>
    <title>🔴 Venice Italy Live Cam - Rialto Bridge in Live Streaming from Palazzo Bembo - Live Webcam - ライブカメラ</title>
    <thumb>https://img.youtube.com/vi/CMn6xQXuSjI/0.jpg</thumb>
    <type>youtube</type>
    <src>CMn6xQXuSjI</src>
  </media><media>
    <title>Inn Street North Live Cam</title>
    <thumb>https://img.youtube.com/vi/WkWyOQ6kQ1M/0.jpg</thumb>
    <type>youtube</type>
    <src>WkWyOQ6kQ1M</src>
  </media><media>
    <title>Plum Island Point Live Cam</title>
    <thumb>https://img.youtube.com/vi/pB_QZmfKZd0/0.jpg</thumb>
    <type>youtube</type>
    <src>pB_QZmfKZd0</src>
  </media><media>
    <title>State Street North Live Cam</title>
    <thumb>https://img.youtube.com/vi/CGrmP5woZz8/0.jpg</thumb>
    <type>youtube</type>
    <src>CGrmP5woZz8</src>
  </media><media>
    <title>Mouth of the Merrimack Live Cam</title>
    <thumb>https://img.youtube.com/vi/L1eldowVJ1Y/0.jpg</thumb>
    <type>youtube</type>
    <src>L1eldowVJ1Y</src>
  </media><media>
    <title>State Street South Live Cam - Newburyport Live Stream</title>
    <thumb>https://img.youtube.com/vi/WkjZg22TBfQ/0.jpg</thumb>
    <type>youtube</type>
    <src>WkjZg22TBfQ</src>
  </media><media>
    <title>🔴 Live Camera Stream | Bondi Aussie Bar &amp;amp; Grill | Chaweng | Koh Samui | Thailand | 2160p 4K</title>
    <thumb>https://img.youtube.com/vi/VR-x3HdhKLQ/0.jpg</thumb>
    <type>youtube</type>
    <src>VR-x3HdhKLQ</src>
  </media><media>
    <title>🔴 Live Camera Stream | Bondi Aussie Bar &amp;amp; Grill | Lamai | Koh Samui | Thailand | 2160p 4K</title>
    <thumb>https://img.youtube.com/vi/w47yvCftkWQ/0.jpg</thumb>
    <type>youtube</type>
    <src>w47yvCftkWQ</src>
  </media><media>
    <title>🔴 El Gaucho | Soi 19 | Sukhumvit Road | Bangkok | Thailand | Live Street Webcam | 2160p 4K</title>
    <thumb>https://img.youtube.com/vi/Q71sLS8h9a4/0.jpg</thumb>
    <type>youtube</type>
    <src>Q71sLS8h9a4</src>
  </media><media>
    <title>🔴 Crystal Bay Beach Resort | Lamai | Koh Samui | Thailand | Live Beach Webcam | 2160p 4K</title>
    <thumb>https://img.youtube.com/vi/Fw9hgttWzIg/0.jpg</thumb>
    <type>youtube</type>
    <src>Fw9hgttWzIg</src>
  </media><media>
    <title>🔴 Soi Green Mango / Munchies Cam | Chaweng | Koh Samui | Thailand | Live Street Webcam</title>
    <thumb>https://img.youtube.com/vi/yFgVmioYkys/0.jpg</thumb>
    <type>youtube</type>
    <src>yFgVmioYkys</src>
  </media><media>
    <title>🕹 LIVE CAMERA PTZ Amazing St. Petersburg Russia Live Chat. Невский пейзаж Санкт-Петербург живой чат</title>
    <thumb>https://img.youtube.com/vi/dhVzWNos718/0.jpg</thumb>
    <type>youtube</type>
    <src>dhVzWNos718</src>
  </media><media>
    <title>4K video LIVE CAMERA Saint Petersburg, Russia. Palace Bridge Дворцовый мост, навигация на Неве</title>
    <thumb>https://img.youtube.com/vi/CjtIYbmVfck/0.jpg</thumb>
    <type>youtube</type>
    <src>CjtIYbmVfck</src>
  </media><media>
    <title>LIVE CAM Zagorodny avenue, St. Petersburg. Веб-камера онлайн Загородный проспект, Санкт-Петербург</title>
    <thumb>https://img.youtube.com/vi/h1wly909BYw/0.jpg</thumb>
    <type>youtube</type>
    <src>h1wly909BYw</src>
  </media><media>
    <title>🕹 LIVE CAMERA Russia Saint Petersburg interactive PTZ control real sound Moscow time online</title>
    <thumb>https://img.youtube.com/vi/VhGdKCs5KIA/0.jpg</thumb>
    <type>youtube</type>
    <src>VhGdKCs5KIA</src>
  </media><media>
    <title>LIVE CAMERA Griboedov Canal St. Petersburg Russia. Канал Грибоедова Санкт-Петербург</title>
    <thumb>https://img.youtube.com/vi/zv0-krx4Kmg/0.jpg</thumb>
    <type>youtube</type>
    <src>zv0-krx4Kmg</src>
  </media><media>
    <title>HIDDEN BEAUTY OF CITIES | Discovering Places of Mysterious Beauty</title>
    <thumb>https://img.youtube.com/vi/_e-u4wBzT_8/0.jpg</thumb>
    <type>youtube</type>
    <src>_e-u4wBzT_8</src>
  </media><media>
    <title>Most Beautiful Cities In The World 8K Video Ultra HD With Soft Piano Music - 60 FPS - 8K Nature Film</title>
    <thumb>https://img.youtube.com/vi/TZikBxNaaQk/0.jpg</thumb>
    <type>youtube</type>
    <src>TZikBxNaaQk</src>
  </media><media>
    <title>PARADISE 8K Video Ultra HD With Soft Piano Music - 60 FPS - 8K Nature Film</title>
    <thumb>https://img.youtube.com/vi/Tq117lqpr-A/0.jpg</thumb>
    <type>youtube</type>
    <src>Tq117lqpr-A</src>
  </media><media>
    <title>5 Most Beautiful and Unbelievable Cities in The World | 4K Travel Guide</title>
    <thumb>https://img.youtube.com/vi/_q0yBz6h4Lg/0.jpg</thumb>
    <type>youtube</type>
    <src>_q0yBz6h4Lg</src>
  </media><media>
    <title>🎄 4K CHRISTMAS SERENITY | Scenic Relaxation with Timeless Holiday Melodies 🎅</title>
    <thumb>https://img.youtube.com/vi/oYTxGDUQfgI/0.jpg</thumb>
    <type>youtube</type>
    <src>oYTxGDUQfgI</src>
  </media><media>
    <title>🔴PHILIPPINES Street View Live camera (1), Soliman Street, Agdao, Davao City #philippines #livestream</title>
    <thumb>https://img.youtube.com/vi/Far_aDIwAyw/0.jpg</thumb>
    <type>youtube</type>
    <src>Far_aDIwAyw</src>
  </media><media>
    <title>🔴PHILIPPINES Live camera Outside Lodi&amp;#39;s Eatery, Agdao, Davao City #philippines</title>
    <thumb>https://img.youtube.com/vi/NEoP0H10_VA/0.jpg</thumb>
    <type>youtube</type>
    <src>NEoP0H10_VA</src>
  </media><media>
    <title>🔴 PHILIPPINES Live camera Inside Cynthia Store, Agdao, Davao City #philippines</title>
    <thumb>https://img.youtube.com/vi/d17IkvT4EkQ/0.jpg</thumb>
    <type>youtube</type>
    <src>d17IkvT4EkQ</src>
  </media><media>
    <title>🔴 PHILIPPINES Live camera, Billiards Hall, Bankerohan , Davao City #philippines</title>
    <thumb>https://img.youtube.com/vi/iJ2rAZX2JY4/0.jpg</thumb>
    <type>youtube</type>
    <src>iJ2rAZX2JY4</src>
  </media><media>
    <title>🔴PHILIPPINES Live camera Majah &amp;quot;MJMB store&amp;quot;, Soliman Street, Agdao, Davao City</title>
    <thumb>https://img.youtube.com/vi/8D94_hdxcac/0.jpg</thumb>
    <type>youtube</type>
    <src>8D94_hdxcac</src>
  </media><media>
    <title>Capri 4K – Discover Italy’s Dream Island and Crystal Blue Waters With Deep House Chill 🎵</title>
    <thumb>https://img.youtube.com/vi/vHaXi0LgsLY/0.jpg</thumb>
    <type>youtube</type>
    <src>vHaXi0LgsLY</src>
  </media><media>
    <title>Mallorca 4K - Valldemossa &amp;amp; Turquoise Coves | Mediterranean Island Escape With Deep House Chill ✨</title>
    <thumb>https://img.youtube.com/vi/V1UXquK7C48/0.jpg</thumb>
    <type>youtube</type>
    <src>V1UXquK7C48</src>
  </media><media>
    <title>Bora Bora 4K – Discover Paradise Beaches and Crystal Blue Lagoons With Deep House Chill 🎵</title>
    <thumb>https://img.youtube.com/vi/0ekb5Mzpzfo/0.jpg</thumb>
    <type>youtube</type>
    <src>0ekb5Mzpzfo</src>
  </media><media>
    <title>Bora Bora 4K – Discover Paradise Beaches and Crystal Blue Lagoons With Deep House Chill 🎵</title>
    <thumb>https://img.youtube.com/vi/PBlkk8UDKO8/0.jpg</thumb>
    <type>youtube</type>
    <src>PBlkk8UDKO8</src>
  </media><media>
    <title>Bora Bora 4K – Discover Paradise Beaches and Crystal Blue Lagoons With Deep House Chill 🎵</title>
    <thumb>https://img.youtube.com/vi/vcXC3tuAzoU/0.jpg</thumb>
    <type>youtube</type>
    <src>vcXC3tuAzoU</src>
  </media>
</mediaList>